asyncmy/__init__.py
asyncmy/auth.py
asyncmy/charset.pxd
asyncmy/charset.pyx
asyncmy/connection.pyx
asyncmy/constants/__init__.py
asyncmy/constants/CLIENT.py
asyncmy/constants/COLUMN.py
asyncmy/constants/COMMAND.py
asyncmy/constants/CR.py
asyncmy/constants/ER.py
asyncmy/constants/FIELD_TYPE.py
asyncmy/constants/FLAG.py
asyncmy/constants/SERVER_STATUS.py
asyncmy/contexts.py
asyncmy/converters.pyx
asyncmy/cursors.pyx
asyncmy/errors.pyx
asyncmy/optionfile.py
asyncmy/pool.pyx
asyncmy/protocol.pyx
asyncmy/replication/__init__.py
asyncmy/replication/binlogstream.py
asyncmy/replication/bitmap.py
asyncmy/replication/column.py
asyncmy/replication/constants.py
asyncmy/replication/errors.py
asyncmy/replication/events.py
asyncmy/replication/gtid.py
asyncmy/replication/packets.py
asyncmy/replication/row_events.py
asyncmy/replication/table.py
asyncmy/replication/utils.py
asyncmy/structs.py
asyncmy/version.py
CHANGELOG.md
LICENSE
README.md
asyncmy/charset.c
asyncmy/charset.cp37-win32.pyd
asyncmy/connection.c
asyncmy/connection.cp37-win32.pyd
asyncmy/converters.c
asyncmy/converters.cp37-win32.pyd
asyncmy/cursors.c
asyncmy/cursors.cp37-win32.pyd
asyncmy/errors.c
asyncmy/errors.cp37-win32.pyd
asyncmy/pool.c
asyncmy/pool.cp37-win32.pyd
asyncmy/protocol.c
asyncmy/protocol.cp37-win32.pyd
asyncmy-0.2.9.dist-info/LICENSE
asyncmy-0.2.9.dist-info/METADATA
asyncmy-0.2.9.dist-info/WHEEL
asyncmy-0.2.9.dist-info/RECORD
