Metadata-Version: 2.1
Name: asyncmy
Version: 0.2.9
Summary: A fast asyncio MySQL driver
Home-page: https://github.com/long2ice/asyncmy
License: Apache-2.0
Keywords: driver,asyncio,mysql
Author: long2ice
Author-email: long2ice@gmail.com
Requires-Python: >=3.7,<4.0
Classifier: License :: OSI Approved :: Apache Software License
Classifier: Programming Language :: Python :: 3
Classifier: Programming Language :: Python :: 3.7
Classifier: Programming Language :: Python :: 3.8
Classifier: Programming Language :: Python :: 3.9
Classifier: Programming Language :: Python :: 3.10
Classifier: Programming Language :: Python :: 3.11
Project-URL: Documentation, https://github.com/long2ice/asyncmy
Project-URL: Repository, https://github.com/long2ice/asyncmy.git
